test_postgres/__init__.py
test_postgres-0.1.2.dist-info/WHEEL
test_postgres-0.1.2.dist-info/METADATA
test_postgres-0.1.2.dist-info/RECORD
