Metadata-Version: 2.1
Name: test-postgres
Version: 0.1.2
Summary: Context for PostgreSQL database testing
Home-page: https://github.com/yevhenshymotiuk/test_postgres
Author: Yevhen Shymotiuk
Author-email: yevhenshymotiuk@gmail.com
Requires-Python: >=3.8,<4.0
Classifier: Programming Language :: Python :: 3
Classifier: Programming Language :: Python :: 3.8
Classifier: Programming Language :: Python :: 3.9
Requires-Dist: psycopg2-binary (>=2.8.6,<3.0.0)
Project-URL: Repository, https://github.com/yevhenshymotiuk/test_postgres
